setup.py
jujube_pill/__init__.py
jujube_pill.egg-info/PKG-INFO
jujube_pill.egg-info/SOURCES.txt
jujube_pill.egg-info/dependency_links.txt
jujube_pill.egg-info/entry_points.txt
jujube_pill.egg-info/top_level.txt