Metadata-Version: 1.0
Name: jujube-pill
Version: 0.0.2
Summary: 吃枣药丸
Home-page: https://xx.c
Author: xlzd
Author-email: xlzd
License: UNKNOWN
Platform: UNKNOWN
